pypalo/__init__.py
pypalo/pan/__init__.py
pypalo-0.0.8.dist-info/LICENSE
pypalo-0.0.8.dist-info/METADATA
pypalo-0.0.8.dist-info/WHEEL
pypalo-0.0.8.dist-info/top_level.txt
pypalo-0.0.8.dist-info/RECORD
