Metadata-Version: 2.1
Name: pypalo
Version: 0.0.8
Summary: A Package to interact with the Palo Alto Networks API
Home-page: https://github.com/dstogsdill/pypalo
Author: Donald Stogsdill
Author-email: donny.stogsdill@gmail.com
License: UNKNOWN
Platform: UNKNOWN
Classifier: Programming Language :: Python :: 2
Classifier: Programming Language :: Python :: 2.7
Classifier: Programming Language :: Python :: 3
Classifier: Programming Language :: Python :: 3.7
Classifier: License :: OSI Approved :: MIT License
Classifier: Operating System :: OS Independent
Requires-Dist: pan-python
Requires-Dist: xmltodict
